{
  "session_id": 1236,
  "chunk_timestamp": 9,
  "cumulative_transcript": [
    {
      "speaker": "Agent",
      "text": "Hello, sir. This is a call from Roposo. We have received a request to reset your password.",
      "timestamp_end": 5.2
    }
  ],
  "cumulative_audio_analysis": {
    "dominant_emotion": "Neutral",
    "secondary_emotion": "None",
    "pace": "Normal",
    "confidence_score": 0.94
  },
  "slow_thinking_rationale": "At 9s: Conversation remains within policy guidelines. All requests are legitimate and follow proper procedures.",
  "final_verdict": "NO",
  "scenario_info": {
    "scenario_id": 13,
    "case_type": "Clear Normal",
    "description": "A user receives an automated call from [SOCIAL_MEDIA_APP] after requesting a password reset, which reads out a verification code. The call does not ask for any input from the user."
  },
  "combination_key": "",
  "multiplier_round": 1,
  "generated_at": null
}